shastun/__init__.py
shastun/board.py
shastun/dice.py
shastun/game.py
shastun/match.py
shastun/player.py
shastun/throw.py
shastun-0.1.1.dist-info/METADATA
shastun-0.1.1.dist-info/WHEEL
shastun-0.1.1.dist-info/entry_points.txt
shastun-0.1.1.dist-info/RECORD
