Metadata-Version: 2.1
Name: shastun
Version: 0.1.1
Summary: 
License: MIT
Author: besya
Author-email: gravisbesya@list.ru
Requires-Python: >=3.12,<4.0
Classifier: License :: OSI Approved :: MIT License
Classifier: Programming Language :: Python :: 3
Classifier: Programming Language :: Python :: 3.12
Classifier: Programming Language :: Python :: 3.13
